UArchiver-0.0.4.data/scripts/uarchiver
udl/Base.py
udl/Downloader.py
udl/Loader.py
udl/__init__.py
udl/errors.py
udl/returncodes.py
udl/utils.py
udl/version.py
udl/kernels/thingiverse.py
udl/kernels/youtube_dl.py
UArchiver-0.0.4.dist-info/LICENSE
UArchiver-0.0.4.dist-info/METADATA
UArchiver-0.0.4.dist-info/WHEEL
UArchiver-0.0.4.dist-info/top_level.txt
UArchiver-0.0.4.dist-info/RECORD
