Metadata-Version: 2.1
Name: UArchiver
Version: 0.0.4
Summary: Ultimate Archiver -- A modular archiving tool
Home-page: https://github.com/joshbarrass/UArchiver
Author: joshbarrass
Author-email: josh.barrass.work@gmail.com
License: UNKNOWN
Keywords: downloader archive dump
Platform: UNKNOWN
Classifier: Intended Audience :: End Users/Desktop
Classifier: Natural Language :: English
Classifier: Programming Language :: Python :: 3
Classifier: Operating System :: POSIX :: Linux
Requires-Dist: docopt (>=0.6.2)
Requires-Dist: youtube-dl
